[
{
    "models": [
    {
        "id": 33052,
        "name": "A-Class",
        "year": 2020,
        "makeId": 27,
        "initialPriceDate": "2019-10-12T07:00:00.000Z",
        "dataEffectiveDate": "2020-01-21T08:00:00.000Z",
        "dataReleaseDate": "2020-04-20T07:00:00.000Z",
        "dataComment": ""
    },
    {
        "id": 32870,
        "name": "AMG GT",
        "year": 2020,
        "makeId": 27,
        "initialPriceDate": "2019-08-19T07:00:00.000Z",
        "dataEffectiveDate": "2020-01-01T08:00:00.000Z",
        "dataReleaseDate": "2020-04-11T07:00:00.000Z",
        "dataComment": ""
    },
    {
        "id": 32864,
        "name": "C-Class",
        "year": 2020,
        "makeId": 27,
        "initialPriceDate": "2019-08-29T07:00:00.000Z",
        "dataEffectiveDate": "2020-01-01T08:00:00.000Z",
        "dataReleaseDate": "2020-04-11T07:00:00.000Z",
        "dataComment": ""
    },
    {
        "id": 32991,
        "name": "CLA",
        "year": 2020,
        "makeId": 27,
        "initialPriceDate": "2019-09-23T07:00:00.000Z",
        "dataEffectiveDate": "2020-01-01T08:00:00.000Z",
        "dataReleaseDate": "2020-04-13T07:00:00.000Z",
        "dataComment": ""
    },
    {
        "id": 32874,
        "name": "CLS",
        "year": 2020,
        "makeId": 27,
        "initialPriceDate": "2019-08-16T07:00:00.000Z",
        "dataEffectiveDate": "2020-01-01T08:00:00.000Z",
        "dataReleaseDate": "2020-04-11T07:00:00.000Z",
        "dataComment": ""
    },
    {
        "id": 32892,
        "name": "E-Class",
        "year": 2020,
        "makeId": 27,
        "initialPriceDate": "2019-08-27T07:00:00.000Z",
        "dataEffectiveDate": "2020-01-01T08:00:00.000Z",
        "dataReleaseDate": "2020-04-28T07:00:00.000Z",
        "dataComment": ""
    },
    {
        "id": 33061,
        "name": "G-Class",
        "year": 2020,
        "makeId": 27,
        "initialPriceDate": "2019-10-22T07:00:00.000Z",
        "dataEffectiveDate": "2020-01-01T08:00:00.000Z",
        "dataReleaseDate": "2020-04-11T07:00:00.000Z",
        "dataComment": ""
    },
    {
        "id": 32984,
        "name": "GLA",
        "year": 2020,
        "makeId": 27,
        "initialPriceDate": "2019-09-19T07:00:00.000Z",
        "dataEffectiveDate": "2019-09-05T07:00:00.000Z",
        "dataReleaseDate": "2020-04-11T07:00:00.000Z",
        "dataComment": ""
    },
    {
        "id": 33204,
        "name": "GLB",
        "year": 2020,
        "makeId": 27,
        "initialPriceDate": "2020-01-08T08:00:00.000Z",
        "dataEffectiveDate": "2020-01-01T08:00:00.000Z",
        "dataReleaseDate": "2020-04-11T07:00:00.000Z",
        "dataComment": ""
    },
    {
        "id": 32894,
        "name": "GLC",
        "year": 2020,
        "makeId": 27,
        "initialPriceDate": "2019-08-28T07:00:00.000Z",
        "dataEffectiveDate": "2020-01-01T08:00:00.000Z",
        "dataReleaseDate": "2020-04-11T07:00:00.000Z",
        "dataComment": ""
    },
    {
        "id": 32303,
        "name": "GLE",
        "year": 2020,
        "makeId": 27,
        "initialPriceDate": "2019-03-25T07:00:00.000Z",
        "dataEffectiveDate": "2020-01-01T08:00:00.000Z",
        "dataReleaseDate": "2020-04-20T07:00:00.000Z",
        "dataComment": ""
    },
    {
        "id": 32986,
        "name": "GLS",
        "year": 2020,
        "makeId": 27,
        "initialPriceDate": "2019-09-18T07:00:00.000Z",
        "dataEffectiveDate": "2020-01-01T08:00:00.000Z",
        "dataReleaseDate": "2020-04-04T07:00:00.000Z",
        "dataComment": ""
    },
    {
        "id": 33042,
        "name": "Metris Cargo Van",
        "year": 2020,
        "makeId": 27,
        "initialPriceDate": "2019-09-30T07:00:00.000Z",
        "dataEffectiveDate": "2019-12-19T08:00:00.000Z",
        "dataReleaseDate": "2020-01-21T08:00:00.000Z",
        "dataComment": ""
    },
    {
        "id": 33043,
        "name": "Metris Passenger Van",
        "year": 2020,
        "makeId": 27,
        "initialPriceDate": "2019-09-30T07:00:00.000Z",
        "dataEffectiveDate": "2019-12-19T08:00:00.000Z",
        "dataReleaseDate": "2020-02-13T08:00:00.000Z",
        "dataComment": ""
    },
    {
        "id": 32893,
        "name": "S-Class",
        "year": 2020,
        "makeId": 27,
        "initialPriceDate": "2019-09-23T07:00:00.000Z",
        "dataEffectiveDate": "2020-02-20T08:00:00.000Z",
        "dataReleaseDate": "2020-04-20T07:00:00.000Z",
        "dataComment": ""
    },
    {
        "id": 32924,
        "name": "SL",
        "year": 2020,
        "makeId": 27,
        "initialPriceDate": "2019-09-05T07:00:00.000Z",
        "dataEffectiveDate": "2019-07-02T07:00:00.000Z",
        "dataReleaseDate": "2020-04-11T07:00:00.000Z",
        "dataComment": ""
    },
    {
        "id": 32931,
        "name": "SLC",
        "year": 2020,
        "makeId": 27,
        "initialPriceDate": "2019-09-10T07:00:00.000Z",
        "dataEffectiveDate": "2020-01-01T08:00:00.000Z",
        "dataReleaseDate": "2020-04-11T07:00:00.000Z",
        "dataComment": ""
    },
    {
        "id": 32628,
        "name": "Sprinter Cab Chassis",
        "year": 2020,
        "makeId": 27,
        "initialPriceDate": "2019-06-17T07:00:00.000Z",
        "dataEffectiveDate": "2020-04-08T07:00:00.000Z",
        "dataReleaseDate": "2020-04-14T07:00:00.000Z",
        "dataComment": ""
    },
    {
        "id": 32619,
        "name": "Sprinter Cargo Van",
        "year": 2020,
        "makeId": 27,
        "initialPriceDate": "2019-06-06T07:00:00.000Z",
        "dataEffectiveDate": "2020-04-08T07:00:00.000Z",
        "dataReleaseDate": "2020-04-20T07:00:00.000Z",
        "dataComment": ""
    },
    {
        "id": 32620,
        "name": "Sprinter Crew Van",
        "year": 2020,
        "makeId": 27,
        "initialPriceDate": "2019-06-06T07:00:00.000Z",
        "dataEffectiveDate": "2020-04-08T07:00:00.000Z",
        "dataReleaseDate": "2020-04-20T07:00:00.000Z",
        "dataComment": ""
    },
    {
        "id": 32629,
        "name": "Sprinter Passenger Van",
        "year": 2020,
        "makeId": 27,
        "initialPriceDate": "2019-06-14T07:00:00.000Z",
        "dataEffectiveDate": "2020-04-08T07:00:00.000Z",
        "dataReleaseDate": "2020-04-16T07:00:00.000Z",
        "dataComment": ""
    }]
}]